neophaser/__init__.py
neophaser/__main__.py
neophaser/board.py
neophaser/controllers.py
neophaser/gui.py
neophaser/options.py
neophaser/utils.py
neophaser/visual.py
neophaser/assets/icon.ico
neophaser/assets/icon.png
neophaser-0.2.1.dist-info/METADATA
neophaser-0.2.1.dist-info/WHEEL
neophaser-0.2.1.dist-info/top_level.txt
neophaser-0.2.1.dist-info/RECORD
