Metadata-Version: 2.1
Name: neophaser
Version: 0.2.1
Summary: NEOPHASER; or, audio effects as applied to the retina - an application for applying audio effects to image and video.
Author-email: 8o-COLLECTIVE <ops@8oc.org>
Project-URL: homepage, https://neophaser.library.8oc.org
Project-URL: repository, https://gitlab.com/8o-collective/neophaser
Classifier: Programming Language :: Python :: 3
Classifier: License :: OSI Approved :: MIT License
Classifier: Operating System :: OS Independent
Requires-Python: >=3.7
Requires-Dist: numpy
Requires-Dist: opencv-python
Requires-Dist: pyqt6
Requires-Dist: pedalboard
